{
  "task_id": "TASK-AES-TC-001",
  "from": "PM Agent",
  "to": "Coding Yang",
  "created_at": "2026-03-31T09:55:00+08:00",
  "status": "incoming",
  "priority": "high",
  "type": "testcase",
  "context": {
    "agent": "Coding Yang",
    "workflow_phase": "IDR",
    "project": "AES_Crypto",
    "description": "【IDR阶段】Testcase开发与验证执行"
  },
  "execution": {
    "command": "Coding Yang 任务：开发Testcase并执行验证",
    "steps": [
      "1. 阅读 Verification Plan了解测试点",
      "2. 开发 smoke_test (基本冒烟测试)",
      "3. 开发 direct_test (NIST向量测试)",
      "4. 开发 random_test (约束随机测试)",
      "5. 开发 CTS边界测试 (1-127 bit)",
      "6. 执行仿真并分析结果",
      "7. Git commit & push",
      "8. 更新任务状态为 completed"
    ],
    "key_points": [
      "必须覆盖所有6种模式 (ECB/CBC/CTR/GCM/XTS/CTS)",
      "必须加载NIST SP 800-38A测试向量",
      "CTS必须覆盖1-127 bit所有边界",
      "使用 {{VCS_PATH}} 或 {{VERILATOR_PATH}} 仿真"
    ]
  },
  "requirements": {
    "deliverables": [
      "smoke_test.sv",
      "direct_test.sv",
      "random_test.sv",
      "cts_boundary_test.sv",
      "仿真日志",
      "波形文件 (VCD/FSDB)"
    ],
    "deadline": "2026-04-11",
    "blocking": "TASK-AES-UVM-001"
  },
  "notify": {
    "on_complete": true
  }
}
